.DS_Store
llm_wrap/__init__.py
llm_wrap/llm_response.py
llm_wrap/logger.py
llm_wrap/llms/__init__.py
llm_wrap/llms/claude_api.py
llm_wrap/llms/gpt_api.py
tests/__init__.py
tests/llms/__init__.py
tests/llms/test_claude_api.py
tests/llms/test_gpt_api.py
llm_wrap-0.2.dist-info/METADATA
llm_wrap-0.2.dist-info/WHEEL
llm_wrap-0.2.dist-info/top_level.txt
llm_wrap-0.2.dist-info/RECORD
