Metadata-Version: 2.1
Name: llm-wrap
Version: 0.2
Summary: UNKNOWN
Home-page: https://github.com/sudodo/llm_wrap
Author: Akihito Sudo
Author-email: akihito.s.gm@gmail.com
License: UNKNOWN
Platform: UNKNOWN
Requires-Dist: openai ==1.3.3
Requires-Dist: anthropic ==0.20.0
